MANIFEST.in
README.md
setup.py
django_linksets.egg-info/PKG-INFO
django_linksets.egg-info/SOURCES.txt
django_linksets.egg-info/dependency_links.txt
django_linksets.egg-info/not-zip-safe
django_linksets.egg-info/requires.txt
django_linksets.egg-info/top_level.txt
linksets/__init__.py
linksets/admin.py
linksets/models.py
linksets/tests.py
linksets/utils.py
linksets/templatetags/__init__.py
linksets/templatetags/links.py