Metadata-Version: 1.0
Name: django-linksets
Version: 2.0.2
Summary: A basic model to include administrable linksets      in templates.
Home-page: https://github.com/gethee2anunnery/django-linksets
Author: Sara Perry w/ Nina Pavlich
Author-email: paraserry@gmail.com
License: UNKNOWN
Platform: UNKNOWN
Classifier: Development Status :: 5 - Production/Stable
Classifier: Environment :: Web Environment
Classifier: Framework :: Django
Classifier: Intended Audience :: Developers
Classifier: License :: OSI Approved
Classifier: Operating System :: OS Independent
Classifier: Programming Language :: Python
